LICENSE
MANIFEST.in
README.md
pyproject.toml
setup.cfg
setup.py
custom_user_profile.egg-info/PKG-INFO
custom_user_profile.egg-info/SOURCES.txt
custom_user_profile.egg-info/dependency_links.txt
custom_user_profile.egg-info/requires.txt
custom_user_profile.egg-info/top_level.txt
users/__init__.py
users/admin.py
users/apps.py
users/forms.py
users/managers.py
users/models.py
users/settings.py
users/urls.py
users/views.py
users/static/users/styles.css
users/templates/users/404.html
users/templates/users/base.html
users/templates/users/create.html
users/templates/users/home.html
users/templates/users/login.html
users/templates/users/user_delete.html
users/templates/users/user_detail.html
users/templates/users/user_edit.html
users/templates/users/user_list.html
users/tests/__init__.py
users/tests/test_models.py